<?xml version="1.0"?>
<Event>
  <EventID>20120111104153</EventID>
  <PageTitle>Monthly Bhajanai</PageTitle>
  <MetaKeywords>Monthly Bhajanai</MetaKeywords>
  <MetaDescription>SIS Monthly Bhajanai</MetaDescription>
  <EventHeading>Monthly Bhajanai</EventHeading>
  <EventDate>2012-01-21</EventDate>
  <EventTime>3 pm</EventTime>
  <Address>SINDHI MANDHIR, 3/8 Cricklewood Broadway, NW2 6QD, Tel  0208 908 2546</Address>
  <Maindescription>&lt;![CDATA[&lt;p&gt;Monthly Sampradhaya Bhajanai sponsored by SIS Nambalava&lt;/p&gt;&lt;/br&gt;

&lt;P&gt;&lt;b&gt;FREE ADMISSION&lt;/p&gt;&lt;/b&gt;&lt;/br&gt;

]]&gt;</Maindescription>
</Event>